{
"type": "FeatureCollection",
                                                                                
"features": [
{ "type": "Feature", "properties": { "Name": "07-010", "Description": "descripción: <br>RT_CODIGO: 1102007010<br>COD_MUN: 11020<br>COD_DIST: 07<br>COD_SECC: 010<br>POBLACION: 1088<br>COD_ENT: d12" }, "geometry": { "type": "Polygon", "coordinates": [ [ [ -6.126017, 36.672772, 0.0 ], [ -6.126373, 36.672949, 0.0 ], [ -6.12681, 36.673162, 0.0 ], [ -6.12802, 36.673859, 0.0 ], [ -6.12827, 36.673477, 0.0 ], [ -6.128604, 36.672967, 0.0 ], [ -6.129119, 36.67231, 0.0 ], [ -6.129647, 36.671662, 0.0 ], [ -6.129749, 36.67155, 0.0 ], [ -6.127627, 36.670663, 0.0 ], [ -6.12747, 36.6706, 0.0 ], [ -6.126133, 36.671241, 0.0 ], [ -6.126019, 36.672749, 0.0 ], [ -6.126017, 36.672772, 0.0 ] ] ] } }

]
}
